cloudam_stream/__init__.py
cloudam_stream/actors.py
cloudam_stream/constants.py
cloudam_stream/parameters.py
cloudam_stream/payload.py
cloudam_stream/ports.py
cloudam_stream/streams.py
cloudam_stream/utils.py
cloudam_stream/wrapper.py
cloudam_stream-0.5.2.dist-info/METADATA
cloudam_stream-0.5.2.dist-info/WHEEL
cloudam_stream-0.5.2.dist-info/top_level.txt
cloudam_stream-0.5.2.dist-info/RECORD
